mcp_scholarly/__init__.py
mcp_scholarly/arxiv_search.py
mcp_scholarly/google_scholar.py
mcp_scholarly/server.py
mcp_scholarly-0.1.0.dist-info/METADATA
mcp_scholarly-0.1.0.dist-info/WHEEL
mcp_scholarly-0.1.0.dist-info/entry_points.txt
mcp_scholarly-0.1.0.dist-info/licenses/LICENSE
mcp_scholarly-0.1.0.dist-info/RECORD
