Metadata-Version: 2.4
Name: mcp-scholarly
Version: 0.1.0
Summary: A MCP server to search for accurate academic articles.
Author-email: Aditya Karnam <akarnam37@gmail.com>
License-File: LICENSE
Requires-Python: >=3.11
Requires-Dist: arxiv>=2.1.3
Requires-Dist: free-proxy>=1.1.3
Requires-Dist: mcp>=1.1.2
Requires-Dist: scholarly>=1.7.11
